local_migrator/__init__.py
local_migrator/_class_register.py
local_migrator/_serialize_hooks.py
local_migrator/_testsupport.py
local_migrator/version.py
local_migrator-0.1.10.dist-info/LICENSE.txt
local_migrator-0.1.10.dist-info/METADATA
local_migrator-0.1.10.dist-info/WHEEL
local_migrator-0.1.10.dist-info/entry_points.txt
local_migrator-0.1.10.dist-info/top_level.txt
local_migrator-0.1.10.dist-info/RECORD
