Metadata-Version: 2.1
Name: local-migrator
Version: 0.1.10
Summary: Package for simplify data structures migrations
Author: Grzegorz Bokota
Author-email: g.bokota@uw.edu.pl
License: MIT
Project-URL: Homepage, https://github.com/Czaki/local_migrator
Project-URL: Documentation, https://local-migrator.readthedocs.io/en/latest/
Project-URL: Repository, https://github.com/Czaki/local_migrator
Keywords: migration,persistance
Classifier: Development Status :: 3 - Alpha
Classifier: Programming Language :: Python
Classifier: Operating System :: OS Independent
Classifier: License :: OSI Approved :: MIT License
Classifier: Programming Language :: Python :: 3
Classifier: Programming Language :: Python :: 3 :: Only
Classifier: Programming Language :: Python :: 3.8
Classifier: Programming Language :: Python :: 3.9
Classifier: Programming Language :: Python :: 3.10
Classifier: Programming Language :: Python :: 3.11
Requires-Python: >=3.8
License-File: LICENSE.txt
Requires-Dist: packaging
Provides-Extra: cbor
Requires-Dist: cbor2 ; extra == 'cbor'
Provides-Extra: test
Requires-Dist: pytest >7.0.0 ; extra == 'test'
Requires-Dist: pydantic ; extra == 'test'
Requires-Dist: numpy ; extra == 'test'
Requires-Dist: napari ; extra == 'test'
